efsf/__init__.py
efsf/certificate.py
efsf/crypto.py
efsf/exceptions.py
efsf/record.py
efsf/sealed.py
efsf/store.py
efsf-0.3.0.dist-info/METADATA
efsf-0.3.0.dist-info/WHEEL
efsf-0.3.0.dist-info/top_level.txt
efsf-0.3.0.dist-info/RECORD
