Metadata-Version: 2.4
Name: efsf
Version: 0.3.0
Summary: Ephemeral-First Security Framework - Security through transience
Author: EFSF Contributors
License: Apache-2.0
Project-URL: Homepage, https://github.com/akshat666/ephemeral-first-security-framework
Project-URL: Documentation, https://github.com/akshat666/ephemeral-first-security-framework#readme
Project-URL: Repository, https://github.com/akshat666/ephemeral-first-security-framework.git
Project-URL: Issues, https://github.com/akshat666/ephemeral-first-security-framework/issues
Keywords: security,privacy,ephemeral,encryption,ttl,crypto-shredding,compliance,gdpr,data-protection
Classifier: Development Status :: 3 - Alpha
Classifier: Intended Audience :: Developers
Classifier: License :: OSI Approved :: Apache Software License
Classifier: Operating System :: OS Independent
Classifier: Programming Language :: Python :: 3
Classifier: Programming Language :: Python :: 3.9
Classifier: Programming Language :: Python :: 3.10
Classifier: Programming Language :: Python :: 3.11
Classifier: Programming Language :: Python :: 3.12
Classifier: Topic :: Security
Classifier: Topic :: Security :: Cryptography
Classifier: Typing :: Typed
Requires-Python: >=3.9
Requires-Dist: cryptography>=41.0.0
Requires-Dist: typing_extensions>=4.0.0
Provides-Extra: redis
Requires-Dist: redis>=4.0.0; extra == "redis"
Provides-Extra: all
Requires-Dist: redis>=4.0.0; extra == "all"
Provides-Extra: dev
Requires-Dist: pytest>=7.0.0; extra == "dev"
Requires-Dist: pytest-cov>=4.0.0; extra == "dev"
Requires-Dist: pytest-asyncio>=0.21.0; extra == "dev"
Requires-Dist: black>=23.0.0; extra == "dev"
Requires-Dist: mypy>=1.0.0; extra == "dev"
Requires-Dist: isort>=5.12.0; extra == "dev"
Requires-Dist: ruff>=0.1.0; extra == "dev"
Requires-Dist: redis>=4.0.0; extra == "dev"
